csam/__init__.py
csam/acts.py
csam/fsOperations.py
csam/mem.py
csam/pub.py
csam/sub.py
csam-0.1.0.dist-info/LICENSE
csam-0.1.0.dist-info/METADATA
csam-0.1.0.dist-info/WHEEL
csam-0.1.0.dist-info/RECORD
