Metadata-Version: 2.3
Name: csam
Version: 0.1.0
Summary: Cliente de sistema de almacenamiento en memoria.
Author: Julio Salazar
Author-email: julio.salazar@cinvestav.mx
Requires-Python: >=3.10
Classifier: Programming Language :: Python :: 3
Classifier: Programming Language :: Python :: 3.10
Classifier: Programming Language :: Python :: 3.11
Classifier: Programming Language :: Python :: 3.12
Classifier: Programming Language :: Python :: 3.13
Requires-Dist: certifi (==2025.6.15)
Requires-Dist: charset-normalizer (==3.4.2)
Requires-Dist: idna (==3.10)
Requires-Dist: paho-mqtt (==2.1.0)
Requires-Dist: requests (>=2.32.4,<3.0.0)
Requires-Dist: urllib3 (==2.5.0)
